tplink_ess_lib/__init__.py
tplink_ess_lib/binary.py
tplink_ess_lib/network.py
tplink_ess_lib/protocol.py
tplink_ess_lib-0.4.5.dist-info/METADATA
tplink_ess_lib-0.4.5.dist-info/WHEEL
tplink_ess_lib-0.4.5.dist-info/top_level.txt
tplink_ess_lib-0.4.5.dist-info/RECORD
