Metadata-Version: 2.1
Name: tplink-ess-lib
Version: 0.4.5
Summary: Python package and software for the TP-Link TL-SG105E and TL-SG108E smart switches
Home-page: https://github.com/firstof9/tplink-ess-lib
Author: firstof9
Author-email: firstof9@gmail.com
License: UNKNOWN
Download-URL: https://github.com/firstof9/tplink-ess-lib
Platform: UNKNOWN
Classifier: Development Status :: 4 - Beta
Classifier: Intended Audience :: Developers
Classifier: Natural Language :: English
Classifier: Programming Language :: Python :: 3
Classifier: Programming Language :: Python :: 3.9
Classifier: Programming Language :: Python :: 3.10
Requires-Python: >=3.8
